LICENSE
README.md
setup.py
google_tx/__init__.py
google_tx/constant.py
google_tx.egg-info/PKG-INFO
google_tx.egg-info/SOURCES.txt
google_tx.egg-info/dependency_links.txt
google_tx.egg-info/top_level.txt