Metadata-Version: 1.0
Name: google-tx
Version: 0.0.1
Summary: fork of google_tx with bug fix https://github.com/lushan88a/google_trans_new
Home-page: UNKNOWN
Author: lushan88a
Author-email: UNKNOWN
License: MIT
Platform: UNKNOWN
